text_menu/__init__.py
text_menu/formatting.py
text_menu/menu_user.py
text_menu/text_menu.py
text_menu/url_user.py
text_menu-0.0.1.dist-info/LICENSE
text_menu-0.0.1.dist-info/METADATA
text_menu-0.0.1.dist-info/WHEEL
text_menu-0.0.1.dist-info/top_level.txt
text_menu-0.0.1.dist-info/RECORD
