Metadata-Version: 2.1
Name: text-menu
Version: 0.0.1
Summary: Create simple but useful terminal menus.
Home-page: https://github.com/gcallah/text_menu
Author: Gene Callahan
Author-email: gcallah@mac.com
License: UNKNOWN
Platform: UNKNOWN
Classifier: Programming Language :: Python :: 3
Classifier: License :: OSI Approved :: GNU General Public License v3 (GPLv3)
Classifier: Operating System :: OS Independent
